data_testing_package/__init__.py
data_testing_package/common_methods/__init__.py
data_testing_package/common_methods/parquet_handler.py
data_testing_package/common_methods/utilities.py
data_testing_package-1.0.5.dist-info/METADATA
data_testing_package-1.0.5.dist-info/WHEEL
data_testing_package-1.0.5.dist-info/RECORD
