Metadata-Version: 2.1
Name: data-testing-package
Version: 1.0.5
Summary: BJSS Testing Package
Author: Babatunde Salaam
Author-email: tunde.salaam@bjss.com
Requires-Python: >=3.8.10,<3.9.0
Classifier: Programming Language :: Python :: 3
Requires-Dist: Faker (>=15.3.3,<16.0.0)
Requires-Dist: allure-behave (>=2.8.6,<3.0.0)
Requires-Dist: allure-python-commons (>=2.8.6,<3.0.0)
Requires-Dist: azure-data-tables (>=12.4.0,<13.0.0)
Requires-Dist: azure-identity (>=1.10.0,<2.0.0)
Requires-Dist: azure-mgmt-datafactory (>=2.7.0,<3.0.0)
Requires-Dist: azure-mgmt-subscription (>=3.0.0,<4.0.0)
Requires-Dist: azure-storage-blob (>=12.13.0,<13.0.0)
Requires-Dist: azure-storage-file-datalake (>=12.8.0,<13.0.0)
Requires-Dist: case-converter (>=1.1.0,<2.0.0)
Requires-Dist: docker (>=6.0.1,<7.0.0)
Requires-Dist: numpy (>=1.23.4,<2.0.0)
Requires-Dist: openpyxl (>=3.0.10,<4.0.0)
Requires-Dist: pandas (>=1.5.1,<2.0.0)
Requires-Dist: pyarrow (==14.0.1)
Requires-Dist: pyarrowfs-adlgen2 (>=0.2.4,<0.3.0)
Requires-Dist: pyodbc (>=4.0.34,<5.0.0)
Requires-Dist: pyspark (==3.5.0)
Requires-Dist: pytest (==7.2.0)
Requires-Dist: requests (==2.32.1)
